{"inkVersion":21,"root":[["^\"Ang Kumperensiya ng Bandung noong 1955 ay isang makasaysayang kaganapan para sa mga bansa sa Asya at Aprika.\"","\n","^\"Dito, napag-usapan ang mga isyu ng kolonyalismo at ang pangangailangan ng mga bansa sa Timog-Silangang Asya na makamit ang kanilang kalayaan at pagkakaisa.\"","\n","^\"Matapos ang kumperensiya, naging mas malinaw ang mga hadlang sa pagbuo ng mga matatag na bansa sa Timog-Silangang Asya.\"","\n","^\"Salamat sa iyong pakikinig sa akin. Mag lakbay at making pa sa ibang kwento nila. Alamin ngayon kung ano ang SDG 16.\"","\n","^Quest: hanapin si luna","\n","end",["done",{"#f":5,"#n":"g-0"}],null],"done",{"#f":1}],"listDefs":{}}